tapioca_arbache/__init__.py
tapioca_arbache/exceptions.py
tapioca_arbache/resource_mapping.py
tapioca_arbache/tapioca_arbache.py
tapioca_arbache-3.0.4.dist-info/LICENSE
tapioca_arbache-3.0.4.dist-info/METADATA
tapioca_arbache-3.0.4.dist-info/WHEEL
tapioca_arbache-3.0.4.dist-info/RECORD
