Metadata-Version: 2.1
Name: tapioca-arbache
Version: 3.0.4
Summary: Clients for Arbache's APIs
Author: Leonardo Jose N Silva
Requires-Python: >=3.10.4,<4.0.0
Classifier: Programming Language :: Python :: 3
Classifier: Programming Language :: Python :: 3.11
Classifier: Programming Language :: Python :: 3.12
Requires-Dist: pre-commit (>=2.15.0,<3.0.0)
Requires-Dist: python-status (>=1.0.1,<2.0.0)
Requires-Dist: requests-oauthlib (>=1.3.0,<2.0.0)
Requires-Dist: responses (>=0.13.3,<0.14.0)
Requires-Dist: tapioca-wrapper (>=2.0.1,<3.0.0)
